odoo/addons/account_invoice_base_invoicing_mode/README.rst
odoo/addons/account_invoice_base_invoicing_mode/__init__.py
odoo/addons/account_invoice_base_invoicing_mode/__manifest__.py
odoo/addons/account_invoice_base_invoicing_mode/i18n/account_invoice_base_invoicing_mode.pot
odoo/addons/account_invoice_base_invoicing_mode/models/__init__.py
odoo/addons/account_invoice_base_invoicing_mode/models/account_invoice.py
odoo/addons/account_invoice_base_invoicing_mode/models/queue_job.py
odoo/addons/account_invoice_base_invoicing_mode/models/res_partner.py
odoo/addons/account_invoice_base_invoicing_mode/models/sale_order.py
odoo/addons/account_invoice_base_invoicing_mode/readme/CONTRIBUTORS.rst
odoo/addons/account_invoice_base_invoicing_mode/readme/DESCRIPTION.rst
odoo/addons/account_invoice_base_invoicing_mode/readme/ROADMAP.rst
odoo/addons/account_invoice_base_invoicing_mode/static/description/icon.png
odoo/addons/account_invoice_base_invoicing_mode/static/description/index.html
odoo/addons/account_invoice_base_invoicing_mode/views/res_partner.xml
odoo13_addon_account_invoice_base_invoicing_mode-13.0.1.0.1.dist-info/METADATA
odoo13_addon_account_invoice_base_invoicing_mode-13.0.1.0.1.dist-info/WHEEL
odoo13_addon_account_invoice_base_invoicing_mode-13.0.1.0.1.dist-info/top_level.txt
odoo13_addon_account_invoice_base_invoicing_mode-13.0.1.0.1.dist-info/RECORD
